insulaClient/InsulaApiConfig.py
insulaClient/InsulaClient.py
insulaClient/InsulaQuery.py
insulaClient/InsulaSearch.py
insulaClient/SingletonMemoryManager.py
insulaClient/WorkflowDataManager.py
insulaClient/__init__.py
insulaClient/delete.py
insulaClient/downloadJob_results.py
insulaClient/files_job_result.py
insulaClient/job_logs.py
insulaClient/job_params.py
insulaClient/job_runner.py
insulaClient/job_status.py
insulaClient/logger.py
insulaClient/placeholders.py
insulaClient/results_manager.py
insulaClient/s3.py
insulaClient/step_result.py
insulaClient/utils.py
insulaClient/workflow.py
insulaClient/workflow_manager.py
insulaClient/workflow_step.py
insulaClient/workflow_step_runner.py
insulaclient-0.6.3.dist-info/METADATA
insulaclient-0.6.3.dist-info/WHEEL
insulaclient-0.6.3.dist-info/entry_points.txt
insulaclient-0.6.3.dist-info/licenses/LICENSE.txt
insulaclient-0.6.3.dist-info/RECORD
