Metadata-Version: 2.3
Name: InsulaClient
Version: 0.6.3
Summary: Insula CLient
Author-email: Roberto Di Rienzo <roberto.dirienzo@codelithic.com>, roberto.dirienzo@cgi.com
Maintainer-email: Roberto Di Rienzo <roberto.dirienzo@codelithic.com>
License-File: LICENSE.txt
Keywords: Italia,cgi,client,insula
Classifier: Development Status :: 4 - Beta
Classifier: Programming Language :: Python
Requires-Python: >=3.9
Requires-Dist: boto3
Requires-Dist: pydantic
Requires-Dist: pyyaml
Requires-Dist: requests
Requires-Dist: snakenest==0.3.0
